thefuck_ai_assistant/__init__.py
thefuck_ai_assistant/ai_assistant.py
thefuck_ai_assistant/copy_source.py
thefuck_ai_assistant/installer.py
thefuck_ai_assistant/rule.py
thefuck_ai_assistant/test.py
thefuck_ai_assistant-0.1.0.dist-info/licenses/LICENSE
thefuck_ai_assistant-0.1.0.dist-info/METADATA
thefuck_ai_assistant-0.1.0.dist-info/WHEEL
thefuck_ai_assistant-0.1.0.dist-info/entry_points.txt
thefuck_ai_assistant-0.1.0.dist-info/top_level.txt
thefuck_ai_assistant-0.1.0.dist-info/RECORD
